Workbook

Sheet Absences-Présences
G3: FR Absences/Présences Catalogue
A6: Absences/Présences EuHReka | C6: Used | D6: Paiement | G6: Retenue | J6: Pilotage Paie | V6: Customizing Table Y00BA_VIE_COMPAN
A7: Code Absences/Présences | B7: Libellé Absences | D7: Rubrique Paiement euHReka | E7: Libellé Rubrique paiement | F7: Unité de temps | G7: Rubrique Paiement euHReka | H7: Libellé Rubrique paiement | I7: Unité de temps | J7: Nombre | K7: Montant | L7: Unité de temps | M7: Formule de calcul | N7: Taux horaire | O7: Taux jour | P7: Pénalisant 13ème mois | Q7: Pénalisant Prime de Vacances | R7: Pénalisant Prime d'ancienneté | S7: Pénalisant RATP -> transport | T7: Additional Comments | U7: WD absence name | V7: Taux paiemnt | W7: Taux retenue | X7: Modicateur Eurheka | Y7: Valeur
A8: (01xx) | B8: Congés Payés
A9: 100 | B9: Congés payés acquis | C9: ■ | D9: 3750 | E9: Paiement CP acquis | F9: Jours de paie | G9: 3500 | H9: Retenue CP acquis | I9: Jours de paie | J9: ■ | K9: ■ | L9: Jour | M9: cf questionnaire de paie pour le 10èCP | O9: TJ10 | P9: □ | Q9: □ | R9: □ | S9: □ | T9: CP2 | U9: Vacation plan (Earned) - Congés payés acquis | V9: 07 | W9: 12 | X9: N/R | Y9: N/R
A10: 110 | B10: Congés payés anticipés | C10: ■ | D10: 3760 | E10: Paiement CP anticipés | F10: Jours de paie | G10: 3510 | H10: Retenue CP Anticipés | I10: Jours de paie | J10: ■ | K10: ■ | L10: Jour | M10: cf questionnaire de paie pour le 10èCP | O10: TJ10 | P10: □ | Q10: □ | R10: □ | S10: □ | T10: CP1 | U10: Vacation plan (In Progress) - Congés payés en-cours | V10: 11 | W10: 12 | X10: N/R | Y10: N/R
A11: 120 | B11: Congés payés reliquats | C11: ■ | D11: 3870 | E11: Paiement CP reliquats | F11: Jours de paie | G11: 3630 | H11: Retenue CP reliquats | I11: Jours de paie | J11: ■ | K11: ■ | L11: Jour | M11: cf questionnaire de paie pour le 10èCP | O11: TJ10 | P11: □ | Q11: □ | R11: □ | S11: □ | T11: CP3 | U11: Vacation plan (Earned) - Congés payés acquis - Carryover | V11: 09 | W11: 12 | X11: N/R | Y11: N/R
A12: 130 | B12: Congés de fractionnement | C12: □ | D12: 3790 | E12: Paiement Congés Fraction | F12: Jours de paie | G12: 3540 | H12: Retenue Congés Fraction | I12: Jours de paie | J12: ■ | K12: ■ | L12: Jour | M12: cf questionnaire de paie pour le 10èCP | O12: TJ6 | P12: □ | Q12: □ | R12: □ | S12: □ | V12: 30 | W12: 30 | X12: 06VL1 | Y12: =VLOOKUP(O12,'Taux de valorisation'!A:O,9,FALSE()) -> 12
A13: 140 | B13: Congés d'ancienneté | C13: ■ | D13: 3770 | E13: Paiement Congé d'ancienn. | F13: Jours de paie | G13: 3520 | H13: Retenue Congés d'Ancienn. | I13: Jours de paie | J13: ■ | K13: ■ | L13: Jour | M13: cf questionnaire de paie pour le 10èCP | O13: TJ10 | P13: □ | Q13: □ | R13: □ | S13: □ | U13: Seniority days | V13: 30 | W13: 30 | X13: 06VL1 | Y13: =VLOOKUP(O13,'Taux de valorisation'!A:O,9,FALSE()) -> 16
A14: 150 | B14: Congés cadres | C14: □ | D14: 3780 | E14: Paiement Congés Cadres | F14: Jours de paie | G14: 3530 | H14: Retenue Congés Cadres | I14: Jours de paie | J14: ■ | K14: ■ | L14: Jour | M14: cf questionnaire de paie pour le 10èCP | O14: TJ6 | P14: □ | Q14: □ | R14: □ | S14: □ | V14: 30 | W14: 30 | X14: 06VL1 | Y14: =VLOOKUP(O14,'Taux de valorisation'!A:O,9,FALSE()) -> 12
A15: 160 | B15: Congés conventionnels | C15: □ | D15: 3930 | E15: Paiem. Congés convent. | F15: Jours de paie | G15: 3690 | H15: Ret. Congés convention. | I15: Jours de paie | J15: □ | K15: □ | M15: cf questionnaire de paie pour le 10èCP | P15: □ | Q15: □ | R15: □ | S15: □ | V15: 30 | W15: 30 | X15: 06VL1 | Y15: =VLOOKUP(O15,'Taux de valorisation'!A:O,9,FALSE()) -> #N/A
A16: GAP with euHReka standard
A17: 161 | B17: Congés supplementaire | C17: ■ | D17: 3931 | E17: Paiem. Congés supplemen. | F17: Jours de paie | G17: 3691 | H17: Ret. Congés supplemen. | I17: Jours de paie | J17: ■ | K17: ■ | L17: Jour | O17: TJ10 | P17: □ | Q17: □ | R17: □ | S17: □ | U17: Extra Time vacation | X17: 06VL1 | Y17: =VLOOKUP(O17,'Taux de valorisation'!A:O,9,FALSE()) -> 16
A18: 162 | B18: Solidarite CP | C18: ■ | D18: 3932 | E18: Paiem.Solidarité CP | F18: Jours de paie | G18: 3692 | H18: Ret. Solidarité CP | I18: Jours de paie | J18: ■ | K18: ■ | L18: Jour | O18: TJ10 | P18: □ | Q18: □ | R18: □ | S18: □ | T18: pas de counter | U18: Solidarité to check | Y18: =VLOOKUP(O18,'Taux de valorisation'!A:O,10,FALSE()) -> 8
A19: 163 | B19: Solidarite | C19: ■ | D19: 3933 | E19: Paiem.Solidarité | F19: Jours de paie | G19: 3693 | H19: Retenue Solidarité | I19: Jours de paie | J19: ■ | K19: ■ | L19: Jour | O19: TJ10 | P19: □ | Q19: □ | R19: □ | S19: □ | T19: pas de counter | U19: Solidarité to check | X19: 06VL1 | Y19: =VLOOKUP(O19,'Taux de valorisation'!A:O,9,FALSE()) -> 16
C20: □ | J20: □ | K20: □ | P20: □ | Q20: □ | R20: □ | S20: □ | X20: 06VL1 | Y20: =VLOOKUP(O20,'Taux de valorisation'!A:O,9,FALSE()) -> #N/A
C21: □ | J21: □ | K21: □ | P21: □ | Q21: □ | R21: □ | S21: □ | X21: 06VL1 | Y21: =VLOOKUP(O21,'Taux de valorisation'!A:O,9,FALSE()) -> #N/A
A22: (04xx) | B22: 35h
A23: 400 | B23: RTT | C23: ■ | D23: 3800 | E23: Paiement RTT | F23: Jours de paie | G23: 3550 | H23: Retenue RTT | I23: Jours de paie | J23: ■ | K23: ■ | L23: Jour | O23: TJ10 | P23: □ | Q23: □ | R23: □ | S23: □ | U23: Work Time Reduction | V23: 31 | W23: 31 | X23: 06VL2 | Y23: =VLOOKUP(O23,'Taux de valorisation'!A:O,10,FALSE()) -> 8
A24: 410 | B24: RTT employé | C24: □ | D24: 3800 | E24: Paiement RTT | F24: Jours de paie | G24: 3550 | H24: Retenue RTT | I24: Jours de paie | J24: □ | K24: □ | L24: Jour | P24: □ | Q24: □ | R24: □ | S24: □ | V24: 31 | W24: 31 | X24: 06VL2 | Y24: =VLOOKUP(O24,'Taux de valorisation'!A:O,10,FALSE()) -> #N/A
A25: 420 | B25: RTT employeur | C25: □ | D25: 3800 | E25: Paiement RTT | F25: Jours de paie | G25: 3550 | H25: Retenue RTT | I25: Jours de paie | J25: □ | K25: □ | L25: Jour | P25: □ | Q25: □ | R25: □ | S25: □ | V25: 31 | W25: 31 | X25: 06VL2 | Y25: =VLOOKUP(O25,'Taux de valorisation'!A:O,10,FALSE()) -> #N/A
A26: 430 | B26: CET | C26: □ | D26: 3950 | E26: Paiement CET | F26: Jours de paie | G26: 3450 | H26: Retenue CET | I26: Jours de paie | J26: ■ | K26: ■ | L26: Jour | O26: TJ6 | P26: □ | Q26: □ | R26: □ | S26: □ | V26: 38 | W26: 31 | X26: 06VL2 | Y26: =VLOOKUP(O26,'Taux de valorisation'!A:O,10,FALSE()) -> 6
A27: GAP with euHReka standard
A28: 401 | B28: RTT solidarite | C28: ■ | D28: 3801 | E28: Paiem.Solidarité RTT | F28: Jours de paie | G28: 3551 | H28: Retenue Solidarité RTT | I28: Jours de paie | J28: ■ | K28: ■ | L28: Jour | O28: TJ10 | P28: □ | Q28: □ | R28: □ | S28: □ | T28: pas de counter | U28: Solidarité to check | V28: 31 | W28: 31 | X28: 06VL2 | Y28: =VLOOKUP(O28,'Taux de valorisation'!A:O,10,FALSE()) -> 8
C29: □ | J29: □ | K29: □ | P29: □ | Q29: □ | R29: □ | S29: □ | Y29: =VLOOKUP(O29,'Taux de valorisation'!A:O,10,FALSE()) -> #N/A
A30: (05xx) | B30: Repos Compensateur
A31: 500 | B31: Contrep. Oblig. Repos (H) | C31: □ | D31: 3810 | E31: Paiement Repos Comp Légal | F31: Heures de paie | G31: 3560 | H31: Retenue Repos Comp Légal | I31: Heures de paie | J31: ■ | K31: ■ | L31: Heure | N31: TH2 | P31: □ | Q31: □ | R31: □ | S31: ■ | V31: 32 | W31: 32 | X31: 06VL4 | Y31: =VLOOKUP(O31,'Taux de valorisation'!A:O,11,FALSE()) -> #N/A
A32: 510 | B32: Contrep. Oblig. Repos (J) | C32: □ | D32: 3D10 ?? | E32: Paiement Jour de Pont | F32: Jours de paie | G32: 3A10 ?? | H32: Retenue Jour de Pont | I32: Jours de paie | J32: □ | K32: □ | P32: □ | Q32: □ | R32: □ | S32: □ | X32: 06VL3 ?? | Y32: =VLOOKUP(O32,'Taux de valorisation'!A:O,12,FALSE()) -> #N/A
A33: 520 | B33: Repos compens. équivalent | C33: □ | D33: 3820 | E33: Paiem. Repos Comp Rempl | F33: Jours de paie | G33: 3570 | H33: Retenue Rep Comp Remplac | I33: Jours de paie | J33: □ | K33: □ | P33: □ | Q33: □ | R33: □ | S33: □ | V33: 33 | W33: 33 | X33: 06VL3 | Y33: =VLOOKUP(O33,'Taux de valorisation'!A:O,12,FALSE()) -> #N/A
A34: 530 | B34: Repos compens. modulation | C34: □ | D34: 3830 | E34: Paiem. Repos Comp. Modul. | F34: Jours de paie | G34: 3580 | H34: Retenue Rep Comp Modul | I34: Jours de paie | J34: □ | K34: □ | P34: □ | Q34: □ | R34: □ | S34: □ | V34: 33 | W34: 33 | X34: 06VL3 | Y34: =VLOOKUP(O34,'Taux de valorisation'!A:O,12,FALSE()) -> #N/A
A35: 540 | B35: Recup crédit d'heures J | C35: □ | D35: 3840 | E35: Paiement Crédit d'Heures | F35: Jours de paie | G35: 3590 | H35: Retenue Crédit d'heures | I35: Jours de paie | J35: □ | K35: □ | P35: □ | Q35: □ | R35: □ | S35: □ | V35: 33 | W35: 33 | X35: 06VL3 | Y35: =VLOOKUP(O35,'Taux de valorisation'!A:O,12,FALSE()) -> #N/A
A36: GAP with euHReka standard
C37: □ | J37: □ | K37: □ | O37: TJ6 | P37: □ | Q37: □ | R37: □ | S37: ■ | Y37: =VLOOKUP(O37,'Taux de valorisation'!A:O,12,FALSE()) -> N/R
C38: □ | J38: □ | K38: □ | O38: TJ6 | P38: □ | Q38: □ | R38: □ | S38: □ | Y38: =VLOOKUP(O38,'Taux de valorisation'!A:O,12,FALSE()) -> N/R
C39: □ | J39: □ | K39: □ | O39: TJ6 | P39: □ | Q39: □ | R39: □ | S39: □ | Y39: =VLOOKUP(O39,'Taux de valorisation'!A:O,12,FALSE()) -> N/R
C40: □ | J40: □ | K40: □ | P40: □ | Q40: □ | R40: □ | S40: □ | Y40: =VLOOKUP(O40,'Taux de valorisation'!A:O,12,FALSE()) -> #N/A
A41: (1xxx et 2xxx) | B41: Arrêt de travail
A42: 1100 | B42: Maladie | C42: ■ | D42: 3200 | E42: Paiement Maladie 100% | F42: Jours calendrier | G42: 3000 | H42: Retenue Maladie | I42: Jours calendrier | J42: ■ | K42: ■ | L42: Jour | O42: TJ17 | P42: □ | Q42: □ | R42: □ | S42: ■ | T42: Pénalise RATP si absence tout le mois | U42: Sick Time Off | V42: 34 | W42: 34 | X42: 06VL5 | Y42: =VLOOKUP(O42,'Taux de valorisation'!A:O,13,FALSE()) -> 1
A43: 1100 | B43: Maladie | C43: □ | D43: 3360 | E43: Paiement Maladie 90% | F43: Jours calendrier | G43: 3000 | H43: Retenue Maladie | I43: Jours calendrier | J43: □ | K43: □ | P43: □ | Q43: □ | R43: □ | S43: □ | V43: 34 | W43: 34 | X43: 06VL5 | Y43: =VLOOKUP(O43,'Taux de valorisation'!A:O,13,FALSE()) -> #N/A
A44: 1100 | B44: Maladie | C44: □ | D44: 3210 | E44: Paiement Maladie 75% | F44: Jours calendrier | G44: 3000 | H44: Retenue Maladie | I44: Jours calendrier | J44: □ | K44: □ | P44: □ | Q44: □ | R44: □ | S44: □ | V44: 34 | W44: 34 | X44: 06VL5 | Y44: =VLOOKUP(O44,'Taux de valorisation'!A:O,13,FALSE()) -> #N/A
A45: 1100 | B45: Maladie | C45: □ | D45: 3370 | E45: Paiement Maladie 66,66% | F45: Jours calendrier | G45: 3000 | H45: Retenue Maladie | I45: Jours calendrier | J45: □ | K45: □ | P45: □ | Q45: □ | R45: □ | S45: □ | V45: 34 | W45: 34 | X45: 06VL5 | Y45: =VLOOKUP(O45,'Taux de valorisation'!A:O,13,FALSE()) -> #N/A
A46: 1100 | B46: Maladie | C46: □ | D46: 3220 | E46: Paiement Maladie 50% | F46: Jours calendrier | G46: 3000 | H46: Retenue Maladie | I46: Jours calendrier | J46: □ | K46: □ | P46: □ | Q46: □ | R46: □ | S46: □ | V46: 34 | W46: 34 | X46: 06VL5 | Y46: =VLOOKUP(O46,'Taux de valorisation'!A:O,13,FALSE()) -> #N/A
A47: 1100 | B47: Maladie | C47: ■ | G47: 3000 | H47: Retenue Maladie | I47: Jours calendrier | J47: ■ | K47: ■ | L47: Jour | O47: TJ17 | P47: □ | Q47: □ | R47: □ | S47: □ | V47: 34 | W47: 34 | X47: 06VL5 | Y47: =VLOOKUP(O47,'Taux de valorisation'!A:O,13,FALSE()) -> 1
A48: 1110 | B48: Accident du travail | C48: ■ | D48: 3230 | E48: Paiement ATT 100% | F48: Jours calendrier | G48: 3030 | H48: Retenue ATT | I48: Jours calendrier | J48: ■ | K48: ■ | L48: Jour | O48: TJ17 | P48: □ | Q48: □ | R48: □ | S48: ■ | T48: Pénalise RATP si absence tout le mois | U48: Work accident | V48: 34 | W48: 34 | X48: 06VL5 | Y48: =VLOOKUP(O48,'Taux de valorisation'!A:O,13,FALSE()) -> 1
A49: 1110 | B49: Accident du travail | C49: □ | D49: 3380 | E49: Paiement ATT 90% | F49: Jours calendrier | G49: 3030 | H49: Retenue ATT | I49: Jours calendrier | J49: □ | K49: □ | P49: □ | Q49: □ | R49: □ | S49: □ | V49: 34 | W49: 34 | X49: 06VL5 | Y49: =VLOOKUP(O49,'Taux de valorisation'!A:O,13,FALSE()) -> #N/A
A50: 1110 | B50: Accident du travail | C50: □ | D50: 3240 | E50: Paiement ATT 75% | F50: Jours calendrier | G50: 3030 | H50: Retenue ATT | I50: Jours calendrier | J50: □ | K50: □ | P50: □ | Q50: □ | R50: □ | S50: □ | V50: 34 | W50: 34 | X50: 06VL5 | Y50: =VLOOKUP(O50,'Taux de valorisation'!A:O,13,FALSE()) -> #N/A
A51: 1110 | B51: Accident du travail | C51: □ | D51: 3390 | E51: Paiement ATT 66,66% | F51: Jours calendrier | G51: 3030 | H51: Retenue ATT | I51: Jours calendrier | J51: □ | K51: □ | P51: □ | Q51: □ | R51: □ | S51: □ | V51: 34 | W51: 34 | X51: 06VL5 | Y51: =VLOOKUP(O51,'Taux de valorisation'!A:O,13,FALSE()) -> #N/A
A52: 1110 | B52: Accident du travail | C52: □ | D52: 3250 | E52: Paiement ATT 50% | F52: Jours calendrier | G52: 3030 | H52: Retenue ATT | I52: Jours calendrier | J52: □ | K52: □ | P52: □ | Q52: □ | R52: □ | S52: □ | V52: 34 | W52: 34 | X52: 06VL5 | Y52: =VLOOKUP(O52,'Taux de valorisation'!A:O,13,FALSE()) -> #N/A
A53: 1110 | B53: Accident du travail | C53: ■ | G53: 3030 | H53: Retenue ATT | I53: Jours calendrier | J53: ■ | K53: ■ | L53: Jour | O53: TJ17 | P53: □ | Q53: □ | R53: □ | S53: □ | W53: 34 | X53: 06VL5 | Y53: =VLOOKUP(O53,'Taux de valorisation'!A:O,13,FALSE()) -> 1
A54: 1120 | B54: Accident du trajet | C54: ■ | D54: 3260 | E54: Paiement ATJ 100% | F54: Jours calendrier | G54: 3060 | H54: Retenue Accident trajet | I54: Jours calendrier | J54: ■ | K54: ■ | L54: Jour | O54: TJ17 | P54: □ | Q54: □ | R54: □ | S54: ■ | T54: Pénalise RATP si absence tout le mois | U54: Journey home to work accident | V54: 34 | W54: 34 | X54: 06VL5 | Y54: =VLOOKUP(O54,'Taux de valorisation'!A:O,13,FALSE()) -> 1
A55: 1120 | B55: Accident du trajet | C55: □ | D55: 3V00 | E55: Paiement ATJ 90% | F55: Jours calendrier | G55: 3060 | H55: Retenue Accident trajet | I55: Jours calendrier | J55: □ | K55: □ | P55: □ | Q55: □ | R55: □ | S55: □ | V55: 34 | W55: 34 | X55: 06VL5 | Y55: =VLOOKUP(O55,'Taux de valorisation'!A:O,13,FALSE()) -> #N/A
A56: 1120 | B56: Accident du trajet | C56: □ | D56: 3270 | E56: Paiement ATJ 75% | F56: Jours calendrier | G56: 3060 | H56: Retenue Accident trajet | I56: Jours calendrier | J56: □ | K56: □ | P56: □ | Q56: □ | R56: □ | S56: □ | V56: 34 | W56: 34 | X56: 06VL5 | Y56: =VLOOKUP(O56,'Taux de valorisation'!A:O,13,FALSE()) -> #N/A
A57: 1120 | B57: Accident du trajet | C57: □ | D57: 3V10 | E57: Paiement ATJ 66,66% | F57: Jours calendrier | G57: 3060 | H57: Retenue Accident trajet | I57: Jours calendrier | J57: □ | K57: □ | P57: □ | Q57: □ | R57: □ | S57: □ | V57: 34 | W57: 34 | X57: 06VL5 | Y57: =VLOOKUP(O57,'Taux de valorisation'!A:O,13,FALSE()) -> #N/A
A58: 1120 | B58: Accident du trajet | C58: □ | D58: 3280 | E58: Paiement ATJ 50% | F58: Jours calendrier | G58: 3060 | H58: Retenue Accident trajet | I58: Jours calendrier | J58: □ | K58: □ | P58: □ | Q58: □ | R58: □ | S58: □ | V58: 34 | W58: 34 | X58: 06VL5 | Y58: =VLOOKUP(O58,'Taux de valorisation'!A:O,13,FALSE()) -> #N/A
A59: 1120 | B59: Accident du trajet | C59: ■ | G59: 3060 | H59: Retenue Accident trajet | I59: Jours calendrier | J59: ■ | K59: ■ | L59: Jour | O59: TJ17 | P59: □ | Q59: □ | R59: □ | S59: □ | W59: 34 | X59: 06VL5 | Y59: =VLOOKUP(O59,'Taux de valorisation'!A:O,13,FALSE()) -> 1
A60: 1130 | B60: Maladie professionnelle | C60: ■ | D60: 3290 | E60: Paiement Mal Prof 100% | F60: Jours calendrier | G60: 3090 | H60: Retenue Mal. Prof. | I60: Jours calendrier | J60: ■ | K60: ■ | L60: Jour | O60: TJ17 | P60: □ | Q60: □ | R60: □ | S60: ■ | T60: Pénalise RATP si absence tout le mois | U60: Work reladed illness (occupational disease) | V60: 34 | W60: 34 | X60: 06VL5 | Y60: =VLOOKUP(O60,'Taux de valorisation'!A:O,13,FALSE()) -> 1
A61: 1200 | B61: Mi-temps thérapeutique | C61: ■ | D61: 3271 | E61: Paiem MiTps Thérapeutiq | G61: 3171 | H61: Retenue MiTps Thérapeutiq | I61: Jours calendrier | J61: ■ | K61: ■ | L61: Jour | O61: TJ17 | P61: □ | Q61: □ | R61: □ | S61: □ | U61: Partially uncapable for work | W61: 34 | X61: 06VL5 | Y61: =VLOOKUP(O61,'Taux de valorisation'!A:O,13,FALSE()) -> 1
A62: 1210 | B62: Cure | C62: □ | D62: 3350 | E62: Paiement Cure | F62: Jours calendrier | G62: 3150 | H62: Retenue Cure | I62: Jours calendrier | J62: □ | K62: □ | P62: □ | Q62: □ | R62: □ | S62: □ | V62: 34 | W62: 34 | X62: 06VL5 | Y62: =VLOOKUP(O62,'Taux de valorisation'!A:O,13,FALSE()) -> #N/A
A63: 2100 | B63: Maternité | C63: ■ | D63: 3320 | E63: Paiement Maternité | F63: Jours calendrier | G63: 3120 | H63: Retenue Maternité | I63: Jours calendrier | J63: ■ | K63: ■ | L63: Jour | O63: TJ17 | P63: □ | Q63: □ | R63: □ | S63: ■ | T63: Pénalise RATP si absence tout le mois | U63: Maternity leave | V63: 34 | W63: 34 | X63: 06VL5 | Y63: =VLOOKUP(O63,'Taux de valorisation'!A:O,13,FALSE()) -> 1
A64: 2110 | B64: Maternité prénatale | C64: □ | D64: 3V40 | E64: Paiem. Mater. Pré-nat. | F64: Jours calendrier | G64: 3H40 | H64: Retenue Mater. Pré-nat. | I64: Jours calendrier | J64: □ | K64: □ | P64: □ | Q64: □ | R64: □ | S64: □ | V64: 34 | W64: 34 | X64: 06VL5 | Y64: =VLOOKUP(O64,'Taux de valorisation'!A:O,13,FALSE()) -> #N/A
A65: 2120 | B65: Maternité postnatale | C65: □ | D65: 3V50 | E65: Paiem. Mater. Post-nat. | F65: Jours calendrier | G65: 3H50 | H65: Retenue Mater. Post-nat. | I65: Jours calendrier | J65: □ | K65: □ | P65: □ | Q65: □ | R65: □ | S65: □ | V65: 34 | W65: 34 | X65: 06VL5 | Y65: =VLOOKUP(O65,'Taux de valorisation'!A:O,13,FALSE()) -> #N/A
A66: 2130 | B66: Paternité | C66: ■ | D66: 3330 | E66: Paiement Paternité | F66: Jours calendrier | G66: 3130 | H66: Retenue Paternité | I66: Jours calendrier | J66: ■ | K66: ■ | L66: Jour | O66: TJ17 | P66: □ | Q66: □ | R66: □ | S66: □ | U66: Paternity | W66: 34 | X66: 06VL5 | Y66: =VLOOKUP(O66,'Taux de valorisation'!A:O,13,FALSE()) -> 1
A67: 2140 | B67: Congé d'adoption | C67: ■ | D67: 3321 | E67: Paiement Congé Adoption | F67: Jours calendrier | G67: 3121 | H67: Retenue Congé Adoption | I67: Jours calendrier | J67: ■ | K67: ■ | L67: Jour | O67: TJ17 | P67: □ | Q67: □ | R67: □ | S67: ■ | T67: Pénalise RATP si absence tout le mois | U67: Adoption leave | W67: 34 | X67: 06VL5 | Y67: =VLOOKUP(O67,'Taux de valorisation'!A:O,13,FALSE()) -> 1
A68: 2150 | B68: Congés pahologiques | C68: □ | D68: 3340 | E68: Paiement Congé Pathologiq | F68: Jours calendrier | G68: 3140 | H68: Retenue Congé Pathologiq | I68: Jours calendrier | J68: ■ | K68: ■ | L68: Jour | O68: TJ17 | U68: Maternity leave
A69: GAP with euHReka standard
A70: 1101 | B70: Retenue Invalidité | C70: ■ | G70: 3001 | H70: Retenue Invalidite | S70: ■ | T70: Pénalise RATP si absence tout le mois | U70: Disabillty leave
C71: □ | J71: □ | K71: □ | P71: □ | Q71: □ | R71: □ | S71: □ | X71: 06VL5 | Y71: =VLOOKUP(O71,'Taux de valorisation'!A:O,13,FALSE()) -> #N/A
C72: □ | J72: □ | K72: □ | P72: □ | Q72: □ | R72: □ | S72: □ | X72: 06VL5 | Y72: =VLOOKUP(O72,'Taux de valorisation'!A:O,13,FALSE()) -> #N/A
C73: □ | J73: □ | K73: □ | P73: □ | Q73: □ | R73: □ | S73: □ | X73: 06VL5 | Y73: =VLOOKUP(O73,'Taux de valorisation'!A:O,13,FALSE()) -> #N/A
A74: (3xxx) | B74: Absences diverses payées
A75: 3100 | B75: Absence autorisée payée | C75: ■ | D75: 3850 | E75: Paiem. Abs Autor. Payée | F75: Jours de paie | G75: 3600 | H75: Retenue Abs Autor Payée | I75: Jours de paie | J75: □ | K75: □ | L75: Jour | O75: TJ10 | P75: □ | Q75: □ | R75: □ | S75: □ | U75: Paid Time off | V75: 35 | W75: 35 | X75: 06VL6 | Y75: =VLOOKUP(O75,'Taux de valorisation'!A:O,14,FALSE()) -> 8
A76: 3200 | B76: Jour de pont | C76: □ | D76: 3D10 | E76: Paiement Jour de Pont | F76: Jours de paie | G76: 3A10 | H76: Retenue Jour de Pont | I76: Jours de paie | J76: □ | K76: □ | P76: □ | Q76: □ | R76: □ | S76: □ | V76: 35 | W76: 35 | X76: 06VL6 | Y76: =VLOOKUP(O76,'Taux de valorisation'!A:O,14,FALSE()) -> #N/A
A77: 3110 | B77: Préavis effectué et payé | C77: ■ | D77: 3960 | E77: Paiem. Préav. effectué | F77: Jours de paie | G77: 3460 | H77: Ret. Préav. payé effectué | I77: Jours de paie | J77: □ | K77: ■ | L77: Jour | O77: TJ10 | P77: □ | Q77: □ | R77: □ | S77: □ | U77: Garden leave | V77: 35 | W77: 35 | X77: 06VL6 | Y77: =VLOOKUP(O77,'Taux de valorisation'!A:O,14,FALSE()) -> 8
A78: 3120 | B78: Préavis non effectué payé | C78: ■ | D78: 3970 | E78: Paiem. Préavis non effect | F78: Jours de paie | G78: 3470 | H78: Ret. Préav. payé non eff. | I78: Jours de paie | J78: □ | K78: ■ | L78: Jour | O78: TJ10 | P78: □ | Q78: □ | R78: □ | S78: □ | U78: Garden leave unpaid | V78: 35 | W78: 35 | X78: 06VL6 | Y78: =VLOOKUP(O78,'Taux de valorisation'!A:O,14,FALSE()) -> 8
A79: 3130 | B79: Recherche d'emploi | C79: □ | D79: 3920 | E79: Paiem Recherche d'Emploi | F79: Jours de paie | G79: 3680 | H79: Retenue Recherched'Emploi | I79: Jours de paie | J79: ■ | K79: ■ | L79: Jour | O79: TJ6 | P79: □ | Q79: □ | R79: □ | S79: □ | V79: 35 | W79: 35 | X79: 06VL6 | Y79: =VLOOKUP(O79,'Taux de valorisation'!A:O,14,FALSE()) -> 6
A80: 3140 | B80: Enfant malade | C80: □ | D80: 3890 | E80: Paiem. Abs Enfant malade | F80: Jours de paie | G80: 3650 | H80: Retenue Abs Enfant Malade | I80: Jours de paie | J80: □ | K80: □ | P80: □ | Q80: □ | R80: □ | S80: □ | V80: 35 | W80: 35 | X80: 06VL6 | Y80: =VLOOKUP(O80,'Taux de valorisation'!A:O,14,FALSE()) -> #N/A
A81: 3150 | B81: Congés événmts familliaux | C81: ■ | D81: 3880 | E81: Paiement Abs Even Fam | F81: Jours de paie | G81: 3640 | H81: Retenue Abs Even Familial | I81: Jours de paie | J81: ■ | K81: ■ | L81: Jour | O81: TJ10 | P81: □ | Q81: □ | R81: □ | S81: □ | U81: Personal Time Off - Child wedding | V81: 35 | W81: 35 | X81: 06VL6 | Y81: =VLOOKUP(O81,'Taux de valorisation'!A:O,14,FALSE()) -> 8
A82: 3160 | B82: Congés mariage | C82: ■ | D82: 3880 | E82: Paiement Abs Even Fam | F82: Jours de paie | G82: 3640 | H82: Retenue Abs Even Familial | I82: Jours de paie | J82: ■ | K82: ■ | L82: Jour | O82: TJ10 | P82: □ | Q82: □ | R82: □ | S82: □ | U82: Personal Time Off - Type Wedding, PACS | V82: 35 | W82: 35 | X82: 06VL6 | Y82: =VLOOKUP(O82,'Taux de valorisation'!A:O,14,FALSE()) -> 8
A83: 3170 | B83: Congés naissance | C83: ■ | D83: 3880 | E83: Paiement Abs Even Fam | F83: Jours de paie | G83: 3640 | H83: Retenue Abs Even Familial | I83: Jours de paie | J83: ■ | K83: ■ | L83: Jour | O83: TJ10 | P83: □ | Q83: □ | R83: □ | S83: □ | U83: Personal Time Off - Type Birth, adoption | V83: 35 | W83: 35 | X83: 06VL6 | Y83: =VLOOKUP(O83,'Taux de valorisation'!A:O,14,FALSE()) -> 8
A84: 3180 | B84: Congés décès | C84: ■ | D84: 3880 | E84: Paiement Abs Even Fam | F84: Jours de paie | G84: 3640 | H84: Retenue Abs Even Familial | I84: Jours de paie | J84: ■ | K84: ■ | L84: Jour | O84: TJ10 | P84: □ | Q84: □ | R84: □ | S84: □ | U84: Compassionate leave - Type Death child,husband,… | V84: 35 | W84: 35 | X84: 06VL6 | Y84: =VLOOKUP(O84,'Taux de valorisation'!A:O,14,FALSE()) -> 8
A85: 3190 | B85: Congés déménagement | C85: ■ | D85: 3880 | E85: Paiement Abs Even Fam | F85: Jours de paie | G85: 3640 | H85: Retenue Abs Even Familial | I85: Jours de paie | J85: ■ | K85: ■ | L85: Jour | O85: TJ10 | P85: □ | Q85: □ | R85: □ | S85: □ | U85: Personal Time Off - Type Moving | V85: 35 | W85: 35 | X85: 06VL6 | Y85: =VLOOKUP(O85,'Taux de valorisation'!A:O,14,FALSE()) -> 8
A86: GAP with euHReka standard
A87: 3101 | B87: Absence autorisée payée H | C87: □ | D87: 3851 | E87: Paiem. Abs Autor. Payée H | F87: Heures de paie | G87: 3601 | H87: Retenue Abs Autor Payée H | I87: Heures de paie | J87: ■ | K87: ■ | L87: Heure | O87: TJ10 | P87: □ | Q87: □ | R87: □ | S87: □ | V87: 35 | W87: 35 | X87: 06VL6 | Y87: =VLOOKUP(O87,'Taux de valorisation'!A:O,14,FALSE()) -> 8
A88: 3111 | B88: Préavis effectué et payé H | C88: □ | D88: 3961 | E88: Paiem. Préav. Effectué H | F88: Heures de paie | G88: 3461 | H88: Ret. Préav. payé effectué H | I88: Heures de paie | J88: ■ | K88: ■ | L88: Heure | N88: TH1 | P88: □ | Q88: □ | R88: □ | S88: □ | X88: 06VL6 | Y88: =VLOOKUP(O88,'Taux de valorisation'!A:O,14,FALSE()) -> #N/A
A89: 3121 | B89: Préavis non effectué payé H | C89: □ | D89: 3971 | E89: Paiem. Préavis non effect H | F89: Heures de paie | G89: 3471 | H89: Ret. Préav. payé non eff. H | I89: Heures de paie | J89: ■ | K89: ■ | L89: Heure | N89: TH1 | P89: □ | Q89: □ | R89: □ | S89: □ | X89: 06VL6 | Y89: =VLOOKUP(O89,'Taux de valorisation'!A:O,14,FALSE()) -> #N/A
A90: 3151 | B90: Congés événmts familliaux H | C90: □ | D90: 3881 | E90: Paiement Abs Even Fam H | F90: Heures de paie | G90: 3641 | H90: Retenue Abs Even Familial H | I90: Heures de paie | J90: ■ | K90: ■ | L90: Heure | N90: TH1
A91: 3161 | B91: Congés mariage H | C91: □ | D91: 3881 | E91: Paiement Abs Even Fam H | F91: Heures de paie | G91: 3641 | H91: Retenue Abs Even Familial H | I91: Heures de paie | J91: ■ | K91: ■ | L91: Heure | N91: TH1
A92: 3171 | B92: Congés naissance H | C92: □ | D92: 3881 | E92: Paiement Abs Even Fam H | F92: Heures de paie | G92: 3641 | H92: Retenue Abs Even Familial H | I92: Heures de paie | J92: ■ | K92: ■ | L92: Heure | N92: TH1
A93: 3181 | B93: Congés décès H | C93: □ | D93: 3881 | E93: Paiement Abs Even Fam H | F93: Heures de paie | G93: 3641 | H93: Retenue Abs Even Familial H | I93: Heures de paie | J93: ■ | K93: ■ | L93: Heure | N93: TH1
A94: 3191 | B94: Congés déménagement H | C94: □ | D94: 3881 | E94: Paiement Abs Even Fam H | F94: Heures de paie | G94: 3641 | H94: Retenue Abs Even Familial H | I94: Heures de paie | J94: ■ | K94: ■ | L94: Heure | N94: TH1 | P94: □ | Q94: □ | R94: □ | S94: □ | X94: 06VL6 | Y94: =VLOOKUP(O94,'Taux de valorisation'!A:O,14,FALSE()) -> #N/A
A95: 3112 | B95: congé préavis | C95: □ | D95: 3962 | E95: Pai.Préav. | F95: Jours de paie | G95: 3462 | H95: Abs préavis | I95: Jours de paie | J95: ■ | K95: ■ | L95: Jour | O95: TJ10 | P95: □ | Q95: □ | R95: □ | S95: □ | X95: 06VL6 | Y95: =VLOOKUP(O95,'Taux de valorisation'!A:O,14,FALSE()) -> 8
A96: (4xxx) | B96: Absences diverses non payées
A97: 4100 | B97: Absence autor. non payée | C97: ■ | G97: 3700 | H97: Retenue Abs Autor Non pay | I97: Jours de paie | J97: ■ | K97: ■ | L97: Jour | O97: TJ10 | P97: □ | Q97: □ | R97: □ | S97: ■ | T97: Pénalise RATP si absence tout le mois | U97: Unpaid Leave of Absence | W97: 36 | X97: 06VL7 | Y97: =VLOOKUP(O97,'Taux de valorisation'!A:O,15,FALSE()) -> 8
A98: 4110 | B98: Abs. non autor. non payée | C98: □ | G98: 3710 | H98: Retenue Grève | I98: Jours de paie | J98: □ | K98: □ | O98: TJ10 | P98: □ | Q98: □ | R98: □ | S98: □ | U98: Unauthorized Unpaid Time Off | W98: 36 | X98: 06VL7 | Y98: =VLOOKUP(O98,'Taux de valorisation'!A:O,15,FALSE()) -> 8
A99: 4120 | B99: Mise à pied | C99: □ | G99: 3620 | H99: Mise à pied | I99: Jours de paie | J99: ■ | K99: ■ | L99: Jour | O99: TJ10 | P99: □ | Q99: ■ | R99: □ | S99: □ | T99: attention -> mention interdite sur le BS | W99: 36 | X99: 06VL7 | Y99: =VLOOKUP(O99,'Taux de valorisation'!A:O,15,FALSE()) -> 8
A100: 4130 | B100: Chômage partiel | C100: □ | D100: 3990 | E100: Alloc. Conv Chôm. Part. | F100: Heures d'absence | G100: 3660 | H100: Retenue Chômage partiel | I100: Heures d'absence | J100: □ | K100: □ | P100: □ | Q100: □ | R100: □ | S100: □ | T100: 3900 - Alloc. Spéc Act Partielle | V100: 04 | W100: 04 | X100: N/R | Y100: N/R
A101: 4140 | B101: Chômage technique | C101: □ | D101: 3980 | E101: Paiement Chômage techniq | F101: Jours de paie | G101: 3480 | H101: Retenue Chôm. Technique | I101: Jours de paie | J101: □ | K101: □ | P101: □ | Q101: □ | R101: □ | S101: □ | V101: 36 | W101: 36 | X101: 06VL7 | Y101: =VLOOKUP(O101,'Taux de valorisation'!A:O,15,FALSE()) -> #N/A
A102: 4150 | B102: Absence injustifiée | C102: □ | G102: 3720 | H102: Retenue Abs injustifiée | I102: Jours de paie | J102: ■ | K102: ■ | L102: Jour | O102: TJ10 | P102: □ | Q102: ■ | R102: □ | S102: ■ | W102: 36 | X102: 06VL7 | Y102: =VLOOKUP(O102,'Taux de valorisation'!A:O,15,FALSE()) -> 8
A103: 4160 | B103: Congé parental | C103: ■ | F103: Jours de paie | G103: 3670 | H103: Retenue Congé parental | I103: Jours de paie | J103: ■ | K103: ■ | L103: Jour | O103: TJ10 | P103: □ | Q103: □ | R103: □ | S103: □ | T103: Géré par suspension de contrat | U103: Parental leave | V103: 36 | W103: 36 | X103: 06VL7 | Y103: =VLOOKUP(O103,'Taux de valorisation'!A:O,15,FALSE()) -> 8
A104: 4170 | B104: Congé sabbatique | C104: ■ | G104: 3730 | H104: Retenue Congé Sabbatique | I104: Jours de paie | J104: ■ | K104: ■ | L104: Jour | O104: TJ10 | P104: □ | Q104: □ | R104: □ | S104: □ | T104: Géré par suspension de contrat | U104: Sabbatical leave | W104: 36 | X104: 06VL7 | Y104: =VLOOKUP(O104,'Taux de valorisation'!A:O,15,FALSE()) -> 8
...

Sheet Parameter
A1: Please do not change !
A3: Tax | B3: Regular tax
B4: Exceptional tax
A6: Freq | B6: Automatic
B7: Recurring
B8: Ad-hoc
A10: Sign | B10: Payment
B11: Deduction
A13: Char | B13: Amount
B14: Number
B15: Both
A17: Dec | B17: Yes
B18: No
A21: AcType | B21: C - Expense account (C with EG)
B22: D - Expense account (C w/o EG)
B23: A - Balance sheet account (F with EG)
B24: B - Balance sheet account (F w/o EG)
B25: E - Balance sheet acc with perno (Q with EG)
B26: F - Balance sheet acc with perno (Q w/o EG)
B27: G - Personal customer accounts (D with EG)
B28: H - Personal customer accounts (D w/o EG)
B29: I - Personal vendor accounts (K with EG)
B30: J - Personal vendor accounts (K w/o EG)
B31: K - Check RA balance (FL with EG)
B32: L - Check RA balance (FL w/o EG)
B33: M - Balance sheet acc orig perno only (FO with EG)
... B42: Z - Expense account w/o quantity (CN w/o EG)
A53: /102 | B53: Reg
A54: /103 | B54: Non-Per
A55: /112 | B55: Pen. Reg
A56: N | B56: N
A57: PC47 | B57: Lump Sum
A58: - | B58: -
A70: /152 | B70: Reg
A71: /153 | B71: Non-Per
A72: /158 | B72: Reg Comm.
A73: /162 | B73: Pen. Reg
A74: N | B74: N
A75: PC47 | B75: Lump Sum
... A123: * | B123: *

Sheet Taux de valorisation
A1: Code | B1: Libellé | C1: Taux euHReka | D1: Formule | G1: Rubriques de PY | H1: Waggetype Class =01 | I1: Modif char 06VL1 | J1: Modif char 06VL2 | K1: Modif char 06VL3 | L1: Modif char 06VL4 | M1: Modif char 06VL5 | N1: Modif char 06VL6 | O1: Modif char 06VL7
A2: TH1 | B2: Taux horaire de base | C2: /001 | D2: Salaire de Base / horaire mensuel du salarié | E2: overtim | F2: Primes de fonction | H2: CL01 -> Value = 2 | I2: N/R | J2: N/R | K2: N/R | L2: 1 | M2: 4 | N2: 11 | O2: 11
A3: TH2 | B3: Taux horaire de base + PA | C3: /003 | D3: (Salaire de Base + Prime Ancienneté) / horaire mensuel du salarié | H3: CL01 -> Value = 2 | I3: N/R | J3: N/R | K3: N/R | L3: 2 | M3: 5 | N3: 12 | O3: 12
A4: TH3 | B4: Taux horaire de base + PA + Primes | C4: /004 | D4: (Salaire de Base + Prime Ancienneté + Prime de Fonction) / horaire mensuel du salarié | H4: CL01 -> Value = 2 | I4: N/R | J4: N/R | K4: N/R | L4: 3 | M4: 6 | N4: 13 | O4: 13
A5: TJ1 | B5: Taux jour ouvré Base | C5: /074 | D5: Salaire de Base / Nb de jours ouvrés | H5: CL01 -> Value = 2 | I5: 7 | J5: 4 | K5: 4 | L5: N/R | M5: N/R | N5: 4 | O5: 4
A6: TJ2 | B6: Taux jour fixe 30 jours Base | C6: /075 | D6: Salaire de Base / Constante 30 | H6: CL01 -> Value = 2 | I6: 8 | J6: NS | K6: NS | L6: N/R | M6: N/R | N6: NS | O6: NS
A7: TJ3 | B7: Taux jour fixe 24 jours Base | C7: /076 | D7: Salaire de Base / Constante 24 | H7: CL01 -> Value = 2 | I7: 9 | J7: NS | K7: NS | L7: N/R | M7: N/R | N7: NS | O7: NS
A8: TJ4 | B8: Taux jour 21,66 jours Base | C8: /077 | D8: Salaire de Base / Constante 21,66 | H8: CL01 -> Value = 2 | I8: 10 | J8: 5 | K8: 5 | L8: N/R | M8: N/R | N8: 5 | O8: 5
A9: TJ5 | B9: Taux jour calendaire Base | C9: /078 | D9: Salaire de Base / Nombre de jours calendaires | H9: CL01 -> Value = 2 | I9: 11 | J9: NS | K9: NS | L9: N/R | M9: 2 | N9: NS | O9: NS
A10: TJ6 | B10: Taux jour fixe 22 jours Base | C10: /079 | D10: Salaire de Base / Constante 22 | I10: 12 | J10: 6 | K10: 6 | L10: N/R | M10: N/R | N10: 6 | O10: 6
A11: TJ7 | B11: Taux jour ouvré Base + PA | C11: /084 | D11: (Salaire de Base + Prime Ancienneté) / Nb de jours ouvrés | I11: 13 | J11: 7 | K11: 7 | L11: N/R | M11: N/R | N11: 7 | O11: 7
A12: TJ8 | B12: Taux jour fixe 30 jours Base + PA | C12: /085 | D12: (Salaire de Base + Prime Ancienneté) / Constante 30 | I12: 14 | J12: NS | K12: NS | L12: N/R | M12: N/R | N12: NS | O12: NS
A13: TJ9 | B13: Taux jour fixe 24 jours Base + PA | C13: /086 | D13: (Salaire de Base + Prime Ancienneté) / Constante 24 | I13: 15 | J13: NS | K13: NS | L13: N/R | M13: N/R | N13: NS | O13: NS
A14: TJ10 | B14: Taux jour 21,66 jours Base + PA | C14: /087 | D14: (Salaire de Base + Prime Ancienneté) / Constante 21,66 | I14: 16 | J14: 8 | K14: 8 | L14: N/R | M14: N/R | N14: 8 | O14: 8
A15: TJ11 | B15: Taux jour calendaire Base + PA | C15: /088 | D15: (Salaire de Base + Prime Ancienneté) / Nombre de jours calendaires | I15: 17 | J15: 10 | K15: 10 | L15: N/R | M15: 3 | N15: 10 | O15: 10
A16: TJ12 | B16: Taux jour fixe 22 jours Base + PA | C16: /089 | D16: (Salaire de Base + Prime Ancienneté) / Constante 22 | I16: 18 | J16: 9 | K16: 9 | L16: N/R | M16: N/R | N16: 9 | O16: 9
A17: TJ13 | B17: Taux jour ouvré Base + PA + Primes | C17: /002 | D17: (Salaire de Base + Prime Ancienneté + Prime de Fonction) / Nb de jours ouvrés | I17: 1 | J17: 1 | K17: 1 | L17: N/R | M17: N/R | N17: 1 | O17: 1
A18: TJ14 | B18: Taux jour fixe 30 jours Base + PA + Primes | C18: /095 | D18: (Salaire de Base + Prime Ancienneté + Prime de Fonction) / Constante 30 | I18: 2 | J18: NS | K18: NS | L18: N/R | M18: N/R | N18: NS | O18: NS
A19: TJ15 | B19: Taux jour fixe 24 jours Base + PA + Primes | C19: /096 | D19: (Salaire de Base + Prime Ancienneté + Prime de Fonction) / Constante 24 | I19: 3 | J19: NS | K19: NS | L19: N/R | M19: N/R | N19: NS | O19: NS
A20: TJ16 | B20: Taux jour 21,66 jours Base + PA + Primes | C20: /097 | D20: (Salaire de Base + Prime Ancienneté + Prime de Fonction) / Constante 21,66 | I20: 4 | J20: 2 | K20: 2 | L20: N/R | M20: N/R | N20: 2 | O20: 2
A21: TJ17 | B21: Taux jour calendaire Base + PA + Primes | C21: /098 | D21: (Salaire de Base + Prime Ancienneté + Prime de Fonction) / Nombre de jours calendaires | I21: 5 | J21: NS | K21: NS | L21: N/R | M21: 1 | N21: NS | O21: NS
A22: TJ18 | B22: Taux jour fixe 22 jours Base + PA + Primes | C22: /099 | D22: (Salaire de Base + Prime Ancienneté + Prime de Fonction) / Constante 22 | I22: 6 | J22: 3 | K22: 3 | L22: N/R | M22: N/R | N22: 3 | O22: 3
A23: GAP with euHReka standard
D32: Entrées spécifiques

Sheet Calendrier
A1: Code | B1: Désignation
A2: AI | B2: Absence injustifiée
A3: AJ | B3: Accident de trajet
A4: AN | B4: Absence aut. non pay
A5: AP | B5: Absence aut. payée
A6: AT | B6: AT
A7: CA | B7: Congé d'adoption
A8: CC | B8: Congé création d’ent
A9: CH | B9: Chômage partiel
A10: CP | B10: Congé Payé
A11: CS | B11: Congé sabbatique
A12: CT | B12: Chômage technique
... A31: TT | B31: Mi-temps thérapeutiq
E34: Entrées spécifiques

Sheet Sheet1
A1: 3550 | B1: Retenue RTT
A2: 3550 | B2: Retenue RTT
A3: 3550 | B3: Retenue RTT
A4: 3450 | B4: Retenue CET

Sheet Aide remplissage
A7: Absences/Présences Catalogue
A10: Le but de cet Excel est de documenter toutes les absences/présences nécessaire pour couvrir vos besoins.
B13: Categorie | C13: Titre colonne | D13: Description de chaque colonne
B14: Absences/Présences EuHReka | C14: Code Absences/Présences | D14: C'est le code utilisé dans euHReka. 4 caractères max.
C15: Libellé Absences | D15: Description de l'absence. 25 caractères max.
B16: Paiement | C16: Rubrique Paiement euHReka | D16: Code rubrique euHReka. 4 caractères max.
C17: Libellé Rubrique paiement | D17: Description rubrique euHReka. 25 caractères max.
C18: Unité de temps | D18: Il existe 5 unités de temps pour mesurer la durée d'une absence : - Jours calendrier - Jours d'absence - Heures d'absence - Jours de paie - Heures de paie
B19: Retenue | C19: Rubrique Retenue euHReka | D19: Code rubrique euHReka. 4 caractères max.
C20: Libellé Rubrique Retenue | D20: Description rubrique euHReka. 25 caractères max.
C21: Unité de temps | D21: Il existe 5 unités de temps pour mesurer la durée d'une absence : - Jours calendrier - Jours d'absence - Heures d'absence - Jours de paie - Heures de paie
B22: Pilotage Paie | C22: Nombre | D22: Affichage du nombre d'heure/jour sur le bulletin
C23: Montant | D23: Affichage du montant sur le bulletin
C24: Unité de temps | D24: L'absence est valorisée en heure ou en Jour
C25: Taux horaire | D25: Taux de valorisation (voir Onglet Taux de valorisation).
C26: Taux jour
C27: Pénalisant 13ème mois | D27: Se reporter à la section 5.5.3 du quesionnaire de paie
C28: Pénalisant Prime de Vacance | D28: Se reporter à la section 5.6.4 du quesionnaire de paie
B29: Pilotage Post-Paie | C29: Affichage Bulletin | D29: Affichage de l'absence sur le bulletin de salaire du salarié en dessous de la partie Brute
C30: Affichage Calendrier Bulletin | D30: Affichage du code d'absence dans le calendrier du bulletin de salaire. Pour plus d'information, se reporter à la section 10.1.1.3 du quesitonnaire de paie
C31: Posting FI | D31: Les rubriques de paiement/retenue doivent être postées en Finance | Z31: Automatic
A49: ■
A50: □
